COPYING
MANIFEST.in
README.rst
requirements.txt
setup.py
version.txt
launchdcheckin/__init__.py
launchdcheckin/_impl.py
launchdcheckin/_unix.py
launchdcheckin/_version.py
launchdcheckin/endpoints.py
launchdcheckin.egg-info/PKG-INFO
launchdcheckin.egg-info/SOURCES.txt
launchdcheckin.egg-info/dependency_links.txt
launchdcheckin.egg-info/requires.txt
launchdcheckin.egg-info/top_level.txt
twisted/plugins/launchd.py