Metadata-Version: 1.1
Name: launchdcheckin
Version: 0.13.0.1
Summary: launchd checkin for python and twisted
Home-page: https://github.com/habnabit/launchdcheckin
Author: Aaron Gallagher
Author-email: _@habnab.it
License: ISC
Platform: UNKNOWN
Classifier: Development Status :: 3 - Alpha
Classifier: Framework :: Twisted
Classifier: Intended Audience :: Developers
Classifier: License :: OSI Approved :: ISC License (ISCL)
Classifier: Operating System :: MacOS :: MacOS X
Classifier: Programming Language :: Python :: 2.6
Classifier: Programming Language :: Python :: 2.7
Classifier: Programming Language :: Python :: 2 :: Only
